youtube_video_downloader/__init__.py
youtube_video_downloader/playlist_download.py
youtube_video_downloader/video_download.py
youtube_video_downloader-0.1.2.dist-info/entry_points.txt
youtube_video_downloader-0.1.2.dist-info/METADATA
youtube_video_downloader-0.1.2.dist-info/WHEEL
youtube_video_downloader-0.1.2.dist-info/RECORD
